{
    "name": "CC2650 TI-MCU Development",
    "image": "k620/cc2650_build:1.3",
    "mounts": [
        "source=${localWorkspaceFolder},target=/workspace,type=bind"
    ],
    "workspaceFolder": "/workspace",
    "customizations": {
        "vscode": {
            "extensions": [
                "ms-vscode.cmake-tools",
                "twxs.cmake",
                "vscodevim.vim",
                "ms-vscode.cpptools",
                "mhutchie.git-graph",
                "GitHub.copilot-chat",
                "ms-python.python",
                "ms-python.debugpy",
                "AndenetAlexander.vim-cheatsheet",
                "eamodio.gitlens"
            ]
        }
    }
}